{
    "keywords": [
        "dungeon world",
        "танк",
        "подготовка",
        "чтение"
    ],
    "hero": {
        "spec": "",
        "for_player": "Танк и поддержка. Ты заранее готовишь руны и раздаешь их союзникам.",
        "base": {
            "level": 1,
            "base_hp": 10,
            "dmg": "d6",
            "arm": 0
        },
        "characteristics": {
            "srt": 12,
            "dex": 8,
            "con": 16,
            "int": 10,
            "wis": 15,
            "cha": 13
        },
        "weapons": [
            "Руна щита на камне (+1 arm)",
            "Серп (close,near,control)"
        ],
        "equipment": [
            "дощечки (2)",
            "провизия (3)"
        ],
        "moves": [
            {
                "title": "Знания",
                "text": "Умеешь читать рунический язык"
            },
            {
                "title": "Создание Рун",
                "text": "Требуется 1 доска и безопасное место. При создании брось 2d6+CON",
                "points": [
                    "10+: успех без последствий",
                    "7-9: руна создана и ты либо тратишь дополнительную доску, либо получаешь 2 урона.",
                    "6-: что-то пошло не так, GM делает ход"
                ]
            }
        ]
    },
    "rules": {
        "title": "правила рун",
        "elements": [
            "Максимум 4 активные руны одновременно.",
            "Максимум 3 руны одного типа.",
            "Руны невозможно создать в бою.",
            "Руны можно передать союзникам, они будут считать активными."
        ]
    }
}